BootCI/Fisher_Pitman_paired_test.py
BootCI/__init__.py
BootCI/paired_bootstrap_interval.py
BootCI-1.0.1.dist-info/LICENCE
BootCI-1.0.1.dist-info/METADATA
BootCI-1.0.1.dist-info/WHEEL
BootCI-1.0.1.dist-info/top_level.txt
BootCI-1.0.1.dist-info/RECORD
